{"type":"FeatureCollection","features":[{"type":"Feature","geometry":{"type":"Polygon","coordinates":[[[151.68014815200007,-32.97898584399997],[151.68273501600004,-32.97800099599994],[151.6821826250001,-32.98224672799995],[151.68014815200007,-32.97898584399997]]]},"properties":{"SA1_MAIN16":"11101120837","SA1_7DIG16":"1120837","SA2_MAIN16":"111011208","SA2_5DIG16":"11208","SA2_NAME16":"Charlestown - Dudley","SA3_CODE16":"11101","SA3_NAME16":"Lake Macquarie - East","SA4_CODE16":"111","SA4_NAME16":"Newcastle and Lake Macquarie","GCC_CODE16":"1RNSW","GCC_NAME16":"Rest of NSW","STE_CODE16":"1","STE_NAME16":"New South Wales","AREASQKM16":0.12380000000000001}}]}