{"type":"FeatureCollection","features":[{"type":"Feature","geometry":{"type":"Polygon","coordinates":[[[153.46292100900007,-28.318287003999956],[153.47272600500006,-28.318505007999928],[153.466969005,-28.327191997999932],[153.46292100900007,-28.318287003999956]]]},"properties":{"SA1_MAIN16":"11203125229","SA1_7DIG16":"1125229","SA2_MAIN16":"112031252","SA2_5DIG16":"11252","SA2_NAME16":"Murwillumbah Region","SA3_CODE16":"11203","SA3_NAME16":"Tweed Valley","SA4_CODE16":"112","SA4_NAME16":"Richmond - Tweed","GCC_CODE16":"1RNSW","GCC_NAME16":"Rest of NSW","STE_CODE16":"1","STE_NAME16":"New South Wales","AREASQKM16":1.3416}}]}