{"type":"FeatureCollection","features":[{"type":"Feature","geometry":{"type":"Polygon","coordinates":[[[151.2172681820001,-33.54619697199996],[151.22887094800015,-33.55278524699999],[151.21441001300002,-33.54931300099998],[151.2172681820001,-33.54619697199996]]]},"properties":{"SA1_MAIN16":"12102140414","SA1_7DIG16":"1140414","SA2_MAIN16":"121021404","SA2_5DIG16":"11404","SA2_NAME16":"Berowra - Brooklyn - Cowan","SA3_CODE16":"12102","SA3_NAME16":"Hornsby","SA4_CODE16":"121","SA4_NAME16":"Sydney - North Sydney and Hornsby","GCC_CODE16":"1GSYD","GCC_NAME16":"Greater Sydney","STE_CODE16":"1","STE_NAME16":"New South Wales","AREASQKM16":1.6009}}]}