{"type":"FeatureCollection","features":[{"type":"Feature","geometry":{"type":"Polygon","coordinates":[[[150.81087345900005,-34.011894326999936],[150.81278799400002,-34.01566499699993],[150.80907280500003,-34.01547529799996],[150.81087345900005,-34.011894326999936]]]},"properties":{"SA1_MAIN16":"12302143855","SA1_7DIG16":"1143855","SA2_MAIN16":"123021438","SA2_5DIG16":"11438","SA2_NAME16":"Claymore - Eagle Vale - Raby","SA3_CODE16":"12302","SA3_NAME16":"Campbelltown (NSW)","SA4_CODE16":"123","SA4_NAME16":"Sydney - Outer South West","GCC_CODE16":"1GSYD","GCC_NAME16":"Greater Sydney","STE_CODE16":"1","STE_NAME16":"New South Wales","AREASQKM16":0.11610000000000001}}]}