{"type":"FeatureCollection","features":[{"type":"Feature","geometry":{"type":"Polygon","coordinates":[[[142.50462226,-38.364337175999935],[142.50905496599995,-38.36783132599993],[142.5041153840001,-38.36734514599994],[142.50462226,-38.364337175999935]]]},"properties":{"SA1_MAIN16":"21704147926","SA1_7DIG16":"2147926","SA2_MAIN16":"217041479","SA2_5DIG16":"21479","SA2_NAME16":"Warrnambool - North","SA3_CODE16":"21704","SA3_NAME16":"Warrnambool","SA4_CODE16":"217","SA4_NAME16":"Warrnambool and South West","GCC_CODE16":"2RVIC","GCC_NAME16":"Rest of Vic.","STE_CODE16":"2","STE_NAME16":"Victoria","AREASQKM16":0.15470000000000003}}]}