{"type":"FeatureCollection","features":[{"type":"Feature","geometry":{"type":"Polygon","coordinates":[[[151.91813344400012,-27.59798042099993],[151.91107376,-27.609462870999945],[151.90556923200003,-27.598435057999946],[151.91813344400012,-27.59798042099993]]]},"properties":{"SA1_MAIN16":"31701144717","SA1_7DIG16":"3144717","SA2_MAIN16":"317011447","SA2_5DIG16":"31447","SA2_NAME16":"Drayton - Harristown","SA3_CODE16":"31701","SA3_NAME16":"Toowoomba","SA4_CODE16":"317","SA4_NAME16":"Toowoomba","GCC_CODE16":"3RQLD","GCC_NAME16":"Rest of Qld","STE_CODE16":"3","STE_NAME16":"Queensland","AREASQKM16":1.1219}}]}