{"type":"FeatureCollection","features":[{"type":"Feature","geometry":{"type":"Polygon","coordinates":[[[116.05251198500002,-33.84628499099995],[116.0611340150001,-33.84699799999993],[116.05712700800008,-33.852586997999936],[116.05251198500002,-33.84628499099995]]]},"properties":{"SA1_MAIN16":"50103101706","SA1_7DIG16":"5101706","SA2_MAIN16":"501031017","SA2_5DIG16":"51017","SA2_NAME16":"Bridgetown - Boyup Brook","SA3_CODE16":"50103","SA3_NAME16":"Manjimup","SA4_CODE16":"501","SA4_NAME16":"Bunbury","GCC_CODE16":"5RWAU","GCC_NAME16":"Rest of WA","STE_CODE16":"5","STE_NAME16":"Western Australia","AREASQKM16":0.7093}}]}