{"type":"FeatureCollection","features":[{"type":"Feature","geometry":{"type":"Polygon","coordinates":[[[117.13620501500009,-20.680781006999947],[117.14046055000006,-20.679956683999933],[117.14064899900006,-20.68291999599995],[117.13620501500009,-20.680781006999947]]]},"properties":{"SA1_MAIN16":"51003127314","SA1_7DIG16":"5127314","SA2_MAIN16":"510031273","SA2_5DIG16":"51273","SA2_NAME16":"Roebourne","SA3_CODE16":"51003","SA3_NAME16":"West Pilbara","SA4_CODE16":"510","SA4_NAME16":"Western Australia - Outback (North)","GCC_CODE16":"5RWAU","GCC_NAME16":"Rest of WA","STE_CODE16":"5","STE_NAME16":"Western Australia","AREASQKM16":0.1383}}]}