{"type":"FeatureCollection","features":[{"type":"Feature","geometry":{"type":"Polygon","coordinates":[[[133.82211745400008,-23.689591017999927],[133.833037998,-23.69876699999997],[133.82272751500017,-23.698323240999965],[133.82211745400008,-23.689591017999927]]]},"properties":{"SA1_MAIN16":"70201104818","SA1_7DIG16":"7104818","SA2_MAIN16":"702011048","SA2_5DIG16":"71048","SA2_NAME16":"Larapinta","SA3_CODE16":"70201","SA3_NAME16":"Alice Springs","SA4_CODE16":"702","SA4_NAME16":"Northern Territory - Outback","GCC_CODE16":"7RNTE","GCC_NAME16":"Rest of NT","STE_CODE16":"7","STE_NAME16":"Northern Territory","AREASQKM16":1.0669}}]}