{"type":"FeatureCollection","features":[{"type":"Feature","geometry":{"type":"Polygon","coordinates":[[[143.48703384900014,-9.57138398799998],[143.49616417800004,-9.56112399899996],[143.498203944,-9.561773977999962],[143.48703384900014,-9.57138398799998]]]},"properties":{"ILO_CODE16":"30700503","ILO_NAME16":"Ugar (Stephens) Island","IAR_CODE16":"307005","IAR_NAME16":"Meriam - Eastern Islands","IRE_CODE16":"307","IRE_NAME16":"Torres Strait","STE_CODE16":"3","STE_NAME16":"Queensland","AREASQKM16":0.7444000000000001}}]}